simple_slack_gen/__init__.py
simple_slack_gen/client.py
simple_slack_gen/core/__init__.py
simple_slack_gen/core/api_error.py
simple_slack_gen/core/auth.py
simple_slack_gen/core/base_client.py
simple_slack_gen/core/binary_response.py
simple_slack_gen/core/request.py
simple_slack_gen/core/response.py
simple_slack_gen/core/utils.py
simple_slack_gen/environment.py
simple_slack_gen/resources/chat/__init__.py
simple_slack_gen/resources/chat/client.py
simple_slack_gen/resources/conversations/__init__.py
simple_slack_gen/resources/conversations/client.py
simple_slack_gen/types/models/__init__.py
simple_slack_gen/types/models/channel.py
simple_slack_gen/types/models/list_conversations_response.py
simple_slack_gen/types/models/message.py
simple_slack_gen/types/models/message_response.py
simple_slack_gen/types/params/__init__.py
simple_slack_gen/types/params/new_message.py
simple_slack_gen-0.2.1.dist-info/METADATA
simple_slack_gen-0.2.1.dist-info/WHEEL
simple_slack_gen-0.2.1.dist-info/RECORD
